oracore/__init__.py
oracore/_internal_db.py
oracore/_internal_migration.py
oracore/crypto.py
oracore/data_formats.py
oracore/exceptions.py
oracore/vault.py
oracore/importers/__init__.py
oracore/importers/google_chrome.py
oracore/importers/samsung_pass.py
oracore-1.0.0.dist-info/METADATA
oracore-1.0.0.dist-info/WHEEL
oracore-1.0.0.dist-info/top_level.txt
oracore-1.0.0.dist-info/RECORD
