Metadata-Version: 2.4
Name: oracore
Version: 1.0.0
Summary: A robust, standalone library for handling password vault encryption and database management.
Author-email: EldricArlo <your_email@example.com>
Project-URL: Homepage, https://github.com/EldricArlo/OraciCore
Project-URL: Bug Tracker, https://github.com/EldricArlo/OraciCore/issues
Classifier: Development Status :: 4 - Beta
Classifier: Intended Audience :: Developers
Classifier: License :: OSI Approved :: MIT License
Classifier: Operating System :: OS Independent
Classifier: Programming Language :: Python :: 3
Classifier: Programming Language :: Python :: 3.8
Classifier: Programming Language :: Python :: 3.9
Classifier: Programming Language :: Python :: 3.10
Classifier: Programming Language :: Python :: 3.11
Classifier: Topic :: Security :: Cryptography
Classifier: Topic :: Software Development :: Libraries :: Python Modules
Requires-Python: >=3.8
Requires-Dist: cryptography>=40.0
Requires-Dist: argon2-cffi>=21.0
